commands_ui/__init__.py
commands_ui/app_settings.py
commands_ui/domain.py
commands_ui/forms.py
commands_ui/management_commands.py
commands_ui/models.py
commands_ui/patch.py
commands_ui/tasks.py
commands_ui/urls.py
commands_ui/use_cases.py
commands_ui/views.py
commands_ui/migrations/0001_initial.py
commands_ui/migrations/__init__.py
commands_ui/templates/base.html
commands_ui/templates/jobs/job-detail-history.html
commands_ui/templates/jobs/job-detail.html
commands_ui/templates/jobs/job-history.html
commands_ui/templates/jobs/job-list.html
commands_ui/templates/jobs/job-status.html
commands_ui/templates/jobs/partials/form.html
commands_ui/templates/jobs/partials/job-output.html
commands_ui/templatetags/__init__.py
commands_ui/templatetags/tags_helpers.py
django_commands_ui-0.0.7.dist-info/licenses/LICENSE
django_commands_ui-0.0.7.dist-info/METADATA
django_commands_ui-0.0.7.dist-info/WHEEL
django_commands_ui-0.0.7.dist-info/top_level.txt
django_commands_ui-0.0.7.dist-info/RECORD
