Metadata-Version: 2.4
Name: django-commands-ui
Version: 0.0.7
Summary: Plugin interface to list and execute existing management commands.
Requires-Python: >=3.10
License-File: LICENSE
Requires-Dist: boto3>=1.26.82
Requires-Dist: celery>=5.2.7
Requires-Dist: django_extensions>=3.2.1
Requires-Dist: django-multidb-router>=0.10
Requires-Dist: djangorestframework>=3.14.0
Requires-Dist: xocto>=6.0.0
Provides-Extra: dev
Requires-Dist: black; extra == "dev"
Requires-Dist: isort; extra == "dev"
Requires-Dist: mypy>=0.982; extra == "dev"
Requires-Dist: pre-commit>=2.6.0; extra == "dev"
Dynamic: license-file
